.DS_Store
inference_visualisation/.DS_Store
inference_visualisation/__init__.py
inference_visualisation/frontend/.DS_Store
inference_visualisation/frontend/build/asset-manifest.json
inference_visualisation/frontend/build/bootstrap.min.css
inference_visualisation/frontend/build/index.html
inference_visualisation/frontend/build/precache-manifest.4f478eec3a792613062d27f8d1dcf3c1.js
inference_visualisation/frontend/build/service-worker.js
inference_visualisation/frontend/build/static/js/2.d2b4dac6.chunk.js
inference_visualisation/frontend/build/static/js/2.d2b4dac6.chunk.js.LICENSE.txt
inference_visualisation/frontend/build/static/js/2.d2b4dac6.chunk.js.map
inference_visualisation/frontend/build/static/js/main.b48b1f99.chunk.js
inference_visualisation/frontend/build/static/js/main.b48b1f99.chunk.js.map
inference_visualisation/frontend/build/static/js/runtime-main.44d30fc2.js
inference_visualisation/frontend/build/static/js/runtime-main.44d30fc2.js.map
inference_visualisation-0.0.3.dist-info/LICENSE
inference_visualisation-0.0.3.dist-info/METADATA
inference_visualisation-0.0.3.dist-info/WHEEL
inference_visualisation-0.0.3.dist-info/top_level.txt
inference_visualisation-0.0.3.dist-info/RECORD
