Metadata-Version: 2.1
Name: inference-visualisation
Version: 0.0.3
Summary: UNKNOWN
Home-page: UNKNOWN
Author: Zdenek Hynek
Author-email: zdenek@syntensor.com
License: UNKNOWN
Platform: UNKNOWN
Requires-Python: >=3.6
License-File: LICENSE
Requires-Dist: streamlit (>=0.63)
